{
  "scope": "applets-dsp",
  "entries": [
    {
      "id": "ClientChainApplet",
      "kind": "applet",
      "display_name": "PooDoo Audio Chain",
      "applet_id_string": "CHAIN",
      "purpose": "Shows the TX DSP signal flow as a horizontal strip of stages (EQ, Compressor, Gate, De-Ess, Tube, PUDU, Reverb). Click a stage to bypass it, double-click to open its editor, drag to reorder the chain. A single BYPASS button disables every stage at once. Also hosts the post-PUDU monitor recorder.",
      "source_files": [
        "src/gui/ClientChainApplet.cpp",
        "src/gui/ClientChainApplet.h",
        "src/gui/ClientChainWidget.cpp",
        "src/gui/ClientChainWidget.h"
      ],
      "related_core_files": [
        "src/core/AudioEngine.cpp",
        "src/core/AudioEngine.h"
      ],
      "how_to_open": "Always visible as the top section of the 'PooDoo Audio' (TXDSP) container when that tile is enabled. Toggle the container via the applet-tray button labelled 'PUDU' in the right sidebar.",
      "build_gate": null,
      "requires_radio_connection": false,
      "controls": [
        {
          "label": "TX",
          "kind": "toggle_button",
          "default": "checked",
          "valid_range": null,
          "setting_key": null,
          "behavior": "Shows and edits the TX DSP chain (the interactive, fully-implemented mode).",
          "notes": "Part of an exclusive pair with RX; amber 'PooDoo' colour when selected."
        },
        {
          "label": "RX",
          "kind": "toggle_button",
          "default": "unchecked",
          "valid_range": null,
          "setting_key": null,
          "behavior": "Switches to the RX chain view — currently shows the placeholder 'Client RX chain — coming in a future phase'.",
          "notes": "Placeholder only; BYPASS is a no-op in this mode."
        },
        {
          "label": "BYPASS",
          "kind": "toggle_button",
          "default": "unchecked",
          "valid_range": null,
          "setting_key": null,
          "behavior": "Checked: snapshots the currently-enabled stages and disables all of them. Unchecked: re-enables just the stages that were on before.",
          "notes": "Stages toggled manually while BYPASS was active are preserved outside the snapshot."
        },
        {
          "label": "Record (circle glyph)",
          "kind": "toggle_button",
          "default": "unchecked",
          "valid_range": null,
          "setting_key": null,
          "behavior": "Captures up to 30 s of post-PUDU TX audio; click again to stop (playback starts automatically).",
          "notes": "Tooltip: 'Record up to 30 s of post-PooDoo TX audio (MIC must be set to PC and DAX off).' Only enabled when the mic input is ready and playback is not running. Pulses red while recording."
        },
        {
          "label": "Play (triangle glyph)",
          "kind": "toggle_button",
          "default": "unchecked",
          "valid_range": null,
          "setting_key": null,
          "behavior": "Plays back the captured PUDU audio; click again to cancel.",
          "notes": "Only enabled once a recording exists and recording is not active. Pulses green while playing."
        },
        {
          "label": "Chain stage (Eq)",
          "kind": "drag_handle",
          "default": null,
          "valid_range": null,
          "setting_key": null,
          "behavior": "Single-click toggles bypass for the EQ stage; double-click opens the EQ editor; drag reorders the chain.",
          "notes": "Delegated to ClientChainWidget; hint text below reads 'Click to bypass · Double click to edit · Drag to reorder'."
        },
        {
          "label": "Chain stage (Comp)",
          "kind": "drag_handle",
          "default": null,
          "valid_range": null,
          "setting_key": null,
          "behavior": "Single-click toggles bypass for the compressor; double-click opens the compressor editor; drag reorders.",
          "notes": null
        },
        {
          "label": "Chain stage (Gate)",
          "kind": "drag_handle",
          "default": null,
          "valid_range": null,
          "setting_key": null,
          "behavior": "Single-click toggles bypass for the gate; double-click opens the gate editor; drag reorders.",
          "notes": null
        },
        {
          "label": "Chain stage (DeEss)",
          "kind": "drag_handle",
          "default": null,
          "valid_range": null,
          "setting_key": null,
          "behavior": "Single-click toggles bypass for the de-esser; double-click opens the de-ess editor; drag reorders.",
          "notes": null
        },
        {
          "label": "Chain stage (Tube)",
          "kind": "drag_handle",
          "default": null,
          "valid_range": null,
          "setting_key": null,
          "behavior": "Single-click toggles bypass for the tube saturator; double-click opens the tube editor; drag reorders.",
          "notes": null
        },
        {
          "label": "Chain stage (Enh / PUDU)",
          "kind": "drag_handle",
          "default": null,
          "valid_range": null,
          "setting_key": null,
          "behavior": "Single-click toggles bypass for the PUDU exciter; double-click opens the PUDU editor; drag reorders.",
          "notes": null
        },
        {
          "label": "Chain stage (Reverb)",
          "kind": "drag_handle",
          "default": null,
          "valid_range": null,
          "setting_key": null,
          "behavior": "Single-click toggles bypass for the reverb; double-click opens the reverb editor; drag reorders.",
          "notes": null
        }
      ],
      "persisted_settings": [
        "ClientCompTxChainStages",
        "Applet_TXDSP"
      ],
      "autostart_setting_key": null,
      "indicators": [
        {"label": "TX endpoint indicator", "states": ["idle", "red pulse"], "meaning": "Red pulse while the user is transmitting on their own slice (driven by TransmitModel::moxChanged)."},
        {"label": "MIC ready indicator", "states": ["ready", "not ready"], "meaning": "Enables / disables the record button based on mic source (PC) and DAX state."},
        {"label": "Monitor record pulse", "states": ["idle", "bright red", "dim red"], "meaning": "500 ms pulse while the post-PUDU recorder is capturing audio."},
        {"label": "Monitor play pulse", "states": ["idle", "bright green", "dim green"], "meaning": "500 ms pulse while captured audio is being played back."},
        {"label": "Interaction hint", "states": ["Click to bypass · Double click to edit · Drag to reorder"], "meaning": "Static usage hint, shown only in TX mode."}
      ],
      "related_menu_items": [
        "Right-click the applet tray button 'PUDU' > toggle PooDoo Audio container visibility"
      ],
      "related_user_tasks": [
        "Reorder the TX DSP chain",
        "Bypass every TX stage at once",
        "Re-enable a specific stage after a global bypass",
        "Open a stage's floating editor from the chain",
        "Record up to 30 seconds of post-PUDU TX audio",
        "Play back the captured PUDU audio",
        "Switch between TX chain view and RX placeholder",
        "Visually confirm when TX (MOX) is live"
      ]
    },
    {
      "id": "ClientCompApplet",
      "kind": "applet",
      "display_name": "Compressor",
      "applet_id_string": "CMP",
      "purpose": "TX-side dynamic-range compressor. Shows the static transfer curve with a live 'ball' riding on the current envelope, a horizontal gain-reduction meter (20 dB max), and five tuning knobs so you can tame voice peaks without opening the floating editor.",
      "source_files": [
        "src/gui/ClientCompApplet.cpp",
        "src/gui/ClientCompApplet.h",
        "src/gui/ClientCompCurveWidget.cpp",
        "src/gui/ClientCompKnob.cpp"
      ],
      "related_core_files": [
        "src/core/ClientComp.cpp",
        "src/core/ClientComp.h"
      ],
      "how_to_open": "Sub-container 'COMPRESSOR' inside the PooDoo Audio (TXDSP) parent container. Tile stays hidden until the Compressor stage is enabled (bypass off) via the CHAIN widget or the floating editor.",
      "build_gate": null,
      "requires_radio_connection": false,
      "controls": [
        {
          "label": "Transfer curve",
          "kind": "indicator",
          "default": null,
          "valid_range": null,
          "setting_key": null,
          "behavior": "Compact-mode ClientCompCurveWidget. Draws the input/output transfer curve plus a live ball showing the current envelope level.",
          "notes": "View-only in the applet; editable in the floating ClientCompEditor."
        },
        {
          "label": "Gain-reduction bar",
          "kind": "meter",
          "default": null,
          "valid_range": "0 to 20 dB GR",
          "setting_key": null,
          "behavior": "Horizontal amber strip, right-filled. Scale maxes at 20 dB reduction; a tick at -6 dB marks a typical working amount.",
          "notes": "Refreshed ~30 Hz from ClientComp::gainReductionDb() with MeterSmoother ballistics."
        },
        {
          "label": "Thresh",
          "kind": "knob",
          "default": "-18.0 dB",
          "valid_range": "-60.0 to 0.0 dB",
          "setting_key": "ClientCompTxThresholdDb",
          "behavior": "Linear mapping. Sets the level above which compression starts.",
          "notes": "Label formatted as '-18.0 dB'."
        },
        {
          "label": "Ratio",
          "kind": "knob",
          "default": "3.0",
          "valid_range": "1.0 to 20.0",
          "setting_key": "ClientCompTxRatio",
          "behavior": "Logarithmic mapping (1 * 20^n). Sets how hard peaks are held once threshold is crossed.",
          "notes": "Label formatted as 'X.XX:1'."
        },
        {
          "label": "Attack",
          "kind": "knob",
          "default": "20.0 ms",
          "valid_range": "0.1 to 300.0 ms",
          "setting_key": "ClientCompTxAttackMs",
          "behavior": "Exponential mapping (0.1 * 3000^n). Sets how quickly the compressor clamps down after the threshold is crossed.",
          "notes": "Label formatted 'X.X ms' below 10, 'X ms' above."
        },
        {
          "label": "Release",
          "kind": "knob",
          "default": "200 ms",
          "valid_range": "5 to 2000 ms",
          "setting_key": "ClientCompTxReleaseMs",
          "behavior": "Exponential mapping (5 * 400^n). Sets how quickly gain returns after the input drops back below threshold.",
          "notes": "Label formatted 'X ms'."
        },
        {
          "label": "Makeup",
          "kind": "knob",
          "default": "0.0 dB",
          "valid_range": "-12.0 to 24.0 dB",
          "setting_key": "ClientCompTxMakeupDb",
          "behavior": "Linear mapping. Adds back gain lost to compression.",
          "notes": "Label shows explicit '+' sign for positive values."
        }
      ],
      "persisted_settings": [
        "ClientCompTxEnabled",
        "ClientCompTxThresholdDb",
        "ClientCompTxRatio",
        "ClientCompTxAttackMs",
        "ClientCompTxReleaseMs",
        "ClientCompTxKneeDb",
        "ClientCompTxMakeupDb",
        "ClientCompTxLimEnabled",
        "ClientCompTxLimCeilingDb"
      ],
      "autostart_setting_key": null,
      "indicators": [
        {"label": "Envelope ball", "states": ["resting at threshold line", "moving along curve"], "meaning": "Live input level plotted against the static transfer curve."},
        {"label": "Gain-reduction strip", "states": ["empty", "amber fill", "-6 dB tick"], "meaning": "Amount of dynamic attenuation currently applied by the compressor."}
      ],
      "related_menu_items": [
        "Double-click the Comp stage in the CHAIN widget to open the floating Compressor editor",
        "Right-click the 'COMPRESSOR' sub-container titlebar to float, pop-out, or hide it"
      ],
      "related_user_tasks": [
        "Adjust compressor threshold",
        "Set compression ratio for voice",
        "Tune attack / release for a natural-sounding squeeze",
        "Apply make-up gain after compression",
        "Watch live gain reduction while speaking",
        "Bypass the compressor from the chain",
        "Open the full Compressor editor for knee and limiter controls"
      ]
    },
    {
      "id": "ClientDeEssApplet",
      "kind": "applet",
      "display_name": "De-Esser",
      "applet_id_string": "DESS",
      "purpose": "TX-side de-esser. Tames harsh 'S' and 'T' sibilance by ducking a narrow band when it exceeds a sidechain threshold. Shows the sidechain bandpass response, a 24 dB gain-reduction meter, and four tuning knobs.",
      "source_files": [
        "src/gui/ClientDeEssApplet.cpp",
        "src/gui/ClientDeEssApplet.h",
        "src/gui/ClientDeEssCurveWidget.cpp",
        "src/gui/ClientCompKnob.cpp"
      ],
      "related_core_files": [
        "src/core/ClientDeEss.cpp",
        "src/core/ClientDeEss.h"
      ],
      "how_to_open": "Sub-container 'DESS' inside the PooDoo Audio (TXDSP) parent container. Hidden until the De-Ess stage is enabled via the CHAIN widget or the floating editor.",
      "build_gate": null,
      "requires_radio_connection": false,
      "controls": [
        {
          "label": "Sidechain response curve",
          "kind": "indicator",
          "default": null,
          "valid_range": null,
          "setting_key": null,
          "behavior": "Compact-mode ClientDeEssCurveWidget. Draws the bandpass filter response with a live ball at the current centre frequency.",
          "notes": null
        },
        {
          "label": "Gain-reduction bar",
          "kind": "meter",
          "default": null,
          "valid_range": "0 to 24 dB GR",
          "setting_key": null,
          "behavior": "Horizontal soft-red strip, right-filled. Scale maxes at 24 dB; a tick marks the -6 dB typical amount.",
          "notes": "Refreshed ~30 Hz from ClientDeEss::gainReductionDb()."
        },
        {
          "label": "Freq",
          "kind": "knob",
          "default": "6000 Hz",
          "valid_range": "1000 to 12000 Hz",
          "setting_key": "ClientDeEssTxFrequencyHz",
          "behavior": "Logarithmic mapping (1000 * 12^n). Sets the centre frequency of the sibilance band.",
          "notes": "Label '6.0 kHz' above 1 kHz, 'N Hz' below."
        },
        {
          "label": "Q",
          "kind": "knob",
          "default": "2.00",
          "valid_range": "0.5 to 5.0",
          "setting_key": "ClientDeEssTxQ",
          "behavior": "Linear mapping. Sets the bandwidth of the sibilance band — higher Q = narrower.",
          "notes": "Label 'X.XX'."
        },
        {
          "label": "Thresh",
          "kind": "knob",
          "default": "-30.0 dB",
          "valid_range": "-60.0 to 0.0 dB",
          "setting_key": "ClientDeEssTxThresholdDb",
          "behavior": "Linear mapping. Level above which the de-esser starts attenuating the band.",
          "notes": null
        },
        {
          "label": "Amount",
          "kind": "knob",
          "default": "-6.0 dB",
          "valid_range": "-24.0 to 0.0 dB",
          "setting_key": "ClientDeEssTxAmountDb",
          "behavior": "Linear mapping. Maximum attenuation applied at peak sibilance.",
          "notes": "Values are negative (or zero) because they represent reduction."
        }
      ],
      "persisted_settings": [
        "ClientDeEssTxEnabled",
        "ClientDeEssTxFrequencyHz",
        "ClientDeEssTxQ",
        "ClientDeEssTxThresholdDb",
        "ClientDeEssTxAmountDb"
      ],
      "autostart_setting_key": null,
      "indicators": [
        {"label": "Centre-frequency ball", "states": ["resting on curve peak"], "meaning": "Marks the currently-tuned sibilance centre frequency on the response curve."},
        {"label": "Gain-reduction strip", "states": ["empty", "soft-red fill"], "meaning": "Current attenuation applied to the sibilance band."}
      ],
      "related_menu_items": [
        "Double-click the DeEss stage in the CHAIN widget to open the floating De-Ess editor",
        "Right-click the 'DESS' sub-container titlebar to float, pop-out, or hide it"
      ],
      "related_user_tasks": [
        "Sweep Freq to locate peak sibilance",
        "Narrow or widen the sidechain band with Q",
        "Set threshold just below the loudest 'S' peaks",
        "Dial Amount for the most transparent de-essing",
        "Watch live GR while reading a sibilant phrase",
        "Bypass the de-esser from the chain"
      ]
    },
    {
      "id": "ClientEqApplet",
      "kind": "applet",
      "display_name": "Parametric EQ (Client)",
      "applet_id_string": "CEQ",
      "purpose": "Client-side parametric equalizer for TX and RX paths. Shows a compact live analyzer overlaid with the summed EQ response; use the RX / TX tabs to pick which path you're shaping. Bands are added, removed, and tuned interactively in the separate ClientEqEditor floating window.",
      "source_files": [
        "src/gui/ClientEqApplet.cpp",
        "src/gui/ClientEqApplet.h",
        "src/gui/ClientEqCurveWidget.cpp"
      ],
      "related_core_files": [
        "src/core/ClientEq.cpp",
        "src/core/ClientEq.h"
      ],
      "how_to_open": "Sub-container 'CEQ' inside the PooDoo Audio (TXDSP) parent container. Hidden until the EQ stage is enabled via the CHAIN widget or the floating editor.",
      "build_gate": null,
      "requires_radio_connection": false,
      "controls": [
        {
          "label": "RX",
          "kind": "tab",
          "default": "checked",
          "valid_range": null,
          "setting_key": null,
          "behavior": "Selects the receive-path EQ for display; binds the curve widget to ClientEq RX instance.",
          "notes": "Part of a mutually-exclusive pair with TX. Starts checked."
        },
        {
          "label": "TX",
          "kind": "tab",
          "default": "unchecked",
          "valid_range": null,
          "setting_key": null,
          "behavior": "Selects the transmit-path EQ for display; binds the curve widget to ClientEq TX instance.",
          "notes": null
        },
        {
          "label": "Analyzer / curve area",
          "kind": "indicator",
          "default": null,
          "valid_range": null,
          "setting_key": null,
          "behavior": "ClientEqCurveWidget — 110 px tall. Shows grid, summed EQ response for the selected path, and a live FFT analyzer overlay.",
          "notes": "View-only; editing happens in the floating ClientEqEditor."
        }
      ],
      "persisted_settings": [
        "ClientEqRxEnabled",
        "ClientEqTxEnabled",
        "ClientEqRxBands",
        "ClientEqTxBands"
      ],
      "autostart_setting_key": null,
      "indicators": [
        {"label": "Summed EQ response", "states": ["flat", "shaped"], "meaning": "Cumulative frequency response of all enabled bands for the selected path."},
        {"label": "Live analyzer overlay", "states": ["idle", "running"], "meaning": "Real-time FFT of audio passing through the selected path."}
      ],
      "related_menu_items": [
        "Double-click the EQ stage in the CHAIN widget to open the floating EQ editor",
        "Right-click the 'CEQ' sub-container titlebar to float, pop-out, or hide it"
      ],
      "related_user_tasks": [
        "Switch between viewing RX and TX EQ",
        "See the live spectrum of the selected path",
        "Bypass the EQ stage from the chain",
        "Open the floating editor to add / remove / tune bands",
        "Verify the summed curve matches your mental target"
      ]
    },
    {
      "id": "ClientGateApplet",
      "kind": "applet",
      "display_name": "Noise Gate / Expander",
      "applet_id_string": "GATE",
      "purpose": "TX-side downward expander / noise gate. Silences background noise between words by attenuating audio below a threshold. Shows the static transfer curve with a live input ball, a 40 dB gain-reduction meter, and five tuning knobs.",
      "source_files": [
        "src/gui/ClientGateApplet.cpp",
        "src/gui/ClientGateApplet.h",
        "src/gui/ClientGateCurveWidget.cpp",
        "src/gui/ClientCompKnob.cpp"
      ],
      "related_core_files": [
        "src/core/ClientGate.cpp",
        "src/core/ClientGate.h"
      ],
      "how_to_open": "Sub-container 'GATE' inside the PooDoo Audio (TXDSP) parent container. Hidden until the Gate stage is enabled via the CHAIN widget or the floating editor.",
      "build_gate": null,
      "requires_radio_connection": false,
      "controls": [
        {
          "label": "Transfer curve",
          "kind": "indicator",
          "default": null,
          "valid_range": null,
          "setting_key": null,
          "behavior": "Compact-mode ClientGateCurveWidget. Plots the expander's static transfer curve and a live ball at the current input level.",
          "notes": null
        },
        {
          "label": "Gain-reduction bar",
          "kind": "meter",
          "default": null,
          "valid_range": "0 to 40 dB GR",
          "setting_key": null,
          "behavior": "Horizontal amber strip, right-filled. Scale maxes at 40 dB (gates can cut very deep); a tick at -15 dB marks the soft-expander default floor.",
          "notes": null
        },
        {
          "label": "Thresh",
          "kind": "knob",
          "default": "-40.0 dB",
          "valid_range": "-80.0 to 0.0 dB",
          "setting_key": "ClientGateTxThresholdDb",
          "behavior": "Linear mapping. Level below which the gate starts attenuating.",
          "notes": null
        },
        {
          "label": "Ratio",
          "kind": "knob",
          "default": "2.0",
          "valid_range": "1.0 to 10.0",
          "setting_key": "ClientGateTxRatio",
          "behavior": "Linear mapping. Higher ratios give a harder, more gate-like cut; lower ratios act as a soft downward expander.",
          "notes": "Label 'X.X:1'."
        },
        {
          "label": "Attack",
          "kind": "knob",
          "default": "0.5 ms",
          "valid_range": "0.1 to 100.0 ms",
          "setting_key": "ClientGateTxAttackMs",
          "behavior": "Exponential mapping (0.1 * 1000^n). Sets how quickly the gate opens when input rises above threshold.",
          "notes": "Label 'X.XX ms' below 10 ms, 'X.X ms' above."
        },
        {
          "label": "Release",
          "kind": "knob",
          "default": "100 ms",
          "valid_range": "5 to 2000 ms",
          "setting_key": "ClientGateTxReleaseMs",
          "behavior": "Exponential mapping (5 * 400^n). Sets how quickly the gate closes after input falls.",
          "notes": "Label 'X.X ms' below 100, 'X ms' above."
        },
        {
          "label": "Floor",
          "kind": "knob",
          "default": "-15.0 dB",
          "valid_range": "-80.0 to 0.0 dB",
          "setting_key": "ClientGateTxFloorDb",
          "behavior": "Linear mapping. Maximum attenuation the gate is allowed to apply.",
          "notes": null
        }
      ],
      "persisted_settings": [
        "ClientGateTxEnabled",
        "ClientGateTxThresholdDb",
        "ClientGateTxRatio",
        "ClientGateTxAttackMs",
        "ClientGateTxReleaseMs",
        "ClientGateTxFloorDb"
      ],
      "autostart_setting_key": null,
      "indicators": [
        {"label": "Input ball", "states": ["below threshold", "above threshold"], "meaning": "Shows whether the gate is currently open or closed."},
        {"label": "Gain-reduction strip", "states": ["empty", "amber fill", "-15 dB tick"], "meaning": "Depth of attenuation while the gate is closed."}
      ],
      "related_menu_items": [
        "Double-click the Gate stage in the CHAIN widget to open the floating Gate editor",
        "Right-click the 'GATE' sub-container titlebar to float, pop-out, or hide it"
      ],
      "related_user_tasks": [
        "Set threshold just above room noise floor",
        "Choose gate vs soft-expander behaviour via ratio",
        "Tune attack / release for natural open/close",
        "Set Floor to avoid unnatural silence between words",
        "Watch live GR while not speaking",
        "Bypass the gate from the chain"
      ]
    },
    {
      "id": "ClientPuduApplet",
      "kind": "applet",
      "display_name": "PUDU Exciter",
      "applet_id_string": "PUDU",
      "purpose": "Centrepiece of the PooDoo Audio chain — the PUDU exciter. Aphex-style Aural Exciter + Big Bottom (Even mode) or Behringer-style tanh shaper + bass compressor (Odd mode). Two groups of three knobs: 'Poo' shapes low end, 'Doo' adds presence / air.",
      "source_files": [
        "src/gui/ClientPuduApplet.cpp",
        "src/gui/ClientPuduApplet.h",
        "src/gui/PooDooLogo.cpp",
        "src/gui/ClientCompKnob.cpp"
      ],
      "related_core_files": [
        "src/core/ClientPudu.cpp",
        "src/core/ClientPudu.h"
      ],
      "how_to_open": "Sub-container 'PUDU' inside the PooDoo Audio (TXDSP) parent container. Hidden until the PUDU stage is enabled via the CHAIN widget or the floating editor.",
      "build_gate": null,
      "requires_radio_connection": false,
      "controls": [
        {
          "label": "PooDoo logo",
          "kind": "indicator",
          "default": null,
          "valid_range": null,
          "setting_key": null,
          "behavior": "Animated branded logo that pulses with the wet-signal RMS.",
          "notes": "PooDooLogo widget — 40 px minimum height."
        },
        {
          "label": "Even",
          "kind": "radio_button",
          "default": null,
          "valid_range": null,
          "setting_key": "ClientPuduTxMode",
          "behavior": "Selects Aphex-lineage asymmetric shaping — predominantly even harmonics, warmer, with Big Bottom LF saturation.",
          "notes": "Amber PooDoo-colour when checked. Exclusive with 'Odd'."
        },
        {
          "label": "Odd",
          "kind": "radio_button",
          "default": null,
          "valid_range": null,
          "setting_key": "ClientPuduTxMode",
          "behavior": "Selects Behringer-lineage symmetric tanh shaping — pure odd harmonics, brighter, with a feed-forward bass compressor.",
          "notes": "Exclusive with 'Even'."
        },
        {
          "label": "Poo / Drive",
          "kind": "knob",
          "default": "6.0 dB",
          "valid_range": "0.0 to 24.0 dB",
          "setting_key": "ClientPuduTxPooDriveDb",
          "behavior": "Linear mapping. Drives the low-frequency saturator / compressor harder.",
          "notes": "Label 'X.X dB'. First knob under the 'Poo' bracket label."
        },
        {
          "label": "Poo / Tune",
          "kind": "knob",
          "default": "100 Hz",
          "valid_range": "50 to 160 Hz",
          "setting_key": "ClientPuduTxPooTuneHz",
          "behavior": "Linear mapping. Centres the low-frequency focus band.",
          "notes": "Label 'X Hz'."
        },
        {
          "label": "Poo / Mix",
          "kind": "knob",
          "default": "30 %",
          "valid_range": "0.0 to 1.0",
          "setting_key": "ClientPuduTxPooMix",
          "behavior": "Linear mapping. Blends the enhanced low band back with the dry signal.",
          "notes": "Label displayed as percentage."
        },
        {
          "label": "Doo / Tune",
          "kind": "knob",
          "default": "5000 Hz",
          "valid_range": "1000 to 10000 Hz",
          "setting_key": "ClientPuduTxDooTuneHz",
          "behavior": "Logarithmic mapping (1000 * 10^n). Centres the high-frequency excitement band.",
          "notes": "Label '5.0 kHz' above 1 kHz, 'X Hz' below. First knob under the 'Doo' bracket label."
        },
        {
          "label": "Doo / Air",
          "kind": "knob",
          "default": "6.0 dB",
          "valid_range": "0.0 to 24.0 dB",
          "setting_key": "ClientPuduTxDooHarmonicsDb",
          "behavior": "Linear mapping. Amount of harmonics / 'air' added at the high band.",
          "notes": "Backing setter is ClientPudu::setDooHarmonicsDb — the knob label in the UI is 'Air'."
        },
        {
          "label": "Doo / Mix",
          "kind": "knob",
          "default": "30 %",
          "valid_range": "0.0 to 1.0",
          "setting_key": "ClientPuduTxDooMix",
          "behavior": "Linear mapping. Blends the excited highs back with the dry signal.",
          "notes": "Label displayed as percentage."
        }
      ],
      "persisted_settings": [
        "ClientPuduTxEnabled",
        "ClientPuduTxMode",
        "ClientPuduTxPooDriveDb",
        "ClientPuduTxPooTuneHz",
        "ClientPuduTxPooMix",
        "ClientPuduTxDooTuneHz",
        "ClientPuduTxDooHarmonicsDb",
        "ClientPuduTxDooMix"
      ],
      "autostart_setting_key": null,
      "indicators": [
        {"label": "PooDoo logo pulse", "states": ["idle", "pulsing"], "meaning": "Brightness follows the processed (wet) signal RMS."},
        {"label": "Poo group bracket", "states": ["Poo"], "meaning": "Group label — the three knobs below belong to the low-frequency processor."},
        {"label": "Doo group bracket", "states": ["Doo"], "meaning": "Group label — the three knobs below belong to the high-frequency processor."}
      ],
      "related_menu_items": [
        "Double-click the PUDU (Enh) stage in the CHAIN widget to open the floating PUDU editor",
        "Right-click the 'PUDU' sub-container titlebar to float, pop-out, or hide it"
      ],
      "related_user_tasks": [
        "Pick Aphex (Even) vs Behringer (Odd) character",
        "Dial Poo Drive for LF thickness",
        "Tune Poo to the fundamental of your voice",
        "Blend the Poo enhancement with Mix",
        "Centre Doo on the presence band for your mic",
        "Add air with Doo Harmonics",
        "Blend the Doo excitement with Mix",
        "Bypass PUDU from the chain"
      ]
    },
    {
      "id": "ClientReverbApplet",
      "kind": "applet",
      "display_name": "Reverb",
      "applet_id_string": "REVERB",
      "purpose": "TX-side Freeverb reverb tail. A compact 5-knob row — Size, Decay, Damp, Pre-delay, Mix — adds room or hall ambience to the transmitted voice.",
      "source_files": [
        "src/gui/ClientReverbApplet.cpp",
        "src/gui/ClientReverbApplet.h",
        "src/gui/ClientCompKnob.cpp"
      ],
      "related_core_files": [
        "src/core/ClientReverb.cpp",
        "src/core/ClientReverb.h"
      ],
      "how_to_open": "Sub-container 'REVERB' inside the PooDoo Audio (TXDSP) parent container. Hidden until the Reverb stage is enabled via the CHAIN widget or the floating editor.",
      "build_gate": null,
      "requires_radio_connection": false,
      "controls": [
        {
          "label": "Size",
          "kind": "knob",
          "default": "50 %",
          "valid_range": "0.0 to 1.0",
          "setting_key": "ClientReverbTxSize",
          "behavior": "Linear mapping. Sets the modelled room size.",
          "notes": "Label displayed as percentage."
        },
        {
          "label": "Decay",
          "kind": "knob",
          "default": "1.20 s",
          "valid_range": "0.3 to 5.0 s",
          "setting_key": "ClientReverbTxDecayS",
          "behavior": "Exponential mapping (0.3 * (5.0/0.3)^n, ~16.7x). Sets the reverb tail length.",
          "notes": "Label 'X.XX s'."
        },
        {
          "label": "Damp",
          "kind": "knob",
          "default": "50 %",
          "valid_range": "0.0 to 1.0",
          "setting_key": "ClientReverbTxDamping",
          "behavior": "Linear mapping. Higher values damp high frequencies faster in the tail.",
          "notes": "Label displayed as percentage."
        },
        {
          "label": "Pre",
          "kind": "knob",
          "default": "20 ms",
          "valid_range": "0 to 100 ms",
          "setting_key": "ClientReverbTxPreDelayMs",
          "behavior": "Linear mapping. Pre-delay between the dry signal and the first reflections.",
          "notes": "Label 'X ms'."
        },
        {
          "label": "Mix",
          "kind": "knob",
          "default": "15 %",
          "valid_range": "0.0 to 1.0",
          "setting_key": "ClientReverbTxMix",
          "behavior": "Linear mapping. Dry / wet balance.",
          "notes": "Label displayed as percentage."
        }
      ],
      "persisted_settings": [
        "ClientReverbTxEnabled",
        "ClientReverbTxSize",
        "ClientReverbTxDecayS",
        "ClientReverbTxDamping",
        "ClientReverbTxPreDelayMs",
        "ClientReverbTxMix"
      ],
      "autostart_setting_key": null,
      "indicators": [],
      "related_menu_items": [
        "Double-click the Reverb stage in the CHAIN widget to open the floating Reverb editor",
        "Right-click the 'REVERB' sub-container titlebar to float, pop-out, or hide it"
      ],
      "related_user_tasks": [
        "Set room size for a small or large-hall feel",
        "Tune decay to taste without muddying speech",
        "Reduce the high-end sparkle of the tail with Damp",
        "Offset reflections from the dry signal with Pre",
        "Dial in a subtle Mix — 10-15 % is typical for voice",
        "Bypass reverb from the chain"
      ]
    },
    {
      "id": "ClientTubeApplet",
      "kind": "applet",
      "display_name": "Tube Saturator",
      "applet_id_string": "TUBE",
      "purpose": "TX-side dynamic tube saturator. Adds harmonic richness by shaping the signal through a bias-swept tube model. Shows a transfer curve that bends with Drive / Bias / model, a live input ball, and five tuning knobs.",
      "source_files": [
        "src/gui/ClientTubeApplet.cpp",
        "src/gui/ClientTubeApplet.h",
        "src/gui/ClientTubeCurveWidget.cpp",
        "src/gui/ClientCompKnob.cpp"
      ],
      "related_core_files": [
        "src/core/ClientTube.cpp",
        "src/core/ClientTube.h"
      ],
      "how_to_open": "Sub-container 'TUBE' inside the PooDoo Audio (TXDSP) parent container. Hidden until the Tube stage is enabled via the CHAIN widget or the floating editor.",
      "build_gate": null,
      "requires_radio_connection": false,
      "controls": [
        {
          "label": "Transfer curve",
          "kind": "indicator",
          "default": null,
          "valid_range": null,
          "setting_key": null,
          "behavior": "Compact-mode ClientTubeCurveWidget. Draws the currently-configured tube transfer curve with a live ball at the input.",
          "notes": null
        },
        {
          "label": "Drive",
          "kind": "knob",
          "default": "0.0 dB",
          "valid_range": "0.0 to 24.0 dB",
          "setting_key": "ClientTubeTxDriveDb",
          "behavior": "Linear mapping. Pushes more signal into the tube stage.",
          "notes": "Label 'X.X dB'."
        },
        {
          "label": "Tone",
          "kind": "knob",
          "default": "0.00",
          "valid_range": "-1.0 to 1.0",
          "setting_key": "ClientTubeTxTone",
          "behavior": "Linear mapping. Negative values darken, positive brighten the saturated signal.",
          "notes": "Label 'X.XX'."
        },
        {
          "label": "Bias",
          "kind": "knob",
          "default": "0 %",
          "valid_range": "0.0 to 1.0",
          "setting_key": "ClientTubeTxBiasAmount",
          "behavior": "Linear mapping. Shifts the operating point on the transfer curve, changing the harmonic mix.",
          "notes": "Label displayed as percentage."
        },
        {
          "label": "Output",
          "kind": "knob",
          "default": "0.0 dB",
          "valid_range": "-24.0 to 12.0 dB",
          "setting_key": "ClientTubeTxOutputGainDb",
          "behavior": "Linear mapping. Post-tube make-up / trim gain.",
          "notes": "Label 'X.X dB'."
        },
        {
          "label": "Mix",
          "kind": "knob",
          "default": "100 %",
          "valid_range": "0.0 to 1.0",
          "setting_key": "ClientTubeTxDryWet",
          "behavior": "Linear mapping. Dry / wet blend (100 % = fully saturated signal).",
          "notes": "Label displayed as percentage. Backing setter is ClientTube::setDryWet."
        }
      ],
      "persisted_settings": [
        "ClientTubeTxEnabled",
        "ClientTubeTxDriveDb",
        "ClientTubeTxTone",
        "ClientTubeTxBiasAmount",
        "ClientTubeTxOutputGainDb",
        "ClientTubeTxDryWet"
      ],
      "autostart_setting_key": null,
      "indicators": [
        {"label": "Live input ball", "states": ["riding curve"], "meaning": "Dot moves along the transfer curve at the current input level, visualising the saturation regime."}
      ],
      "related_menu_items": [
        "Double-click the Tube stage in the CHAIN widget to open the floating Tube editor",
        "Right-click the 'TUBE' sub-container titlebar to float, pop-out, or hide it"
      ],
      "related_user_tasks": [
        "Dial Drive until the curve starts to bend",
        "Shift Bias to tweak the even / odd harmonic balance",
        "Brighten or darken the saturated signal with Tone",
        "Compensate level changes with Output",
        "Parallel-blend saturation with Mix",
        "Bypass the tube from the chain"
      ]
    },
    {
      "id": "EqApplet",
      "kind": "applet",
      "display_name": "Equalizer (Graphic)",
      "applet_id_string": "EQ",
      "purpose": "8-band graphic equalizer applied inside the radio itself via the TCP/IP API — separate from the client-side parametric EQ. Fixed bands at 63, 125, 250, 500 Hz and 1, 2, 4, 8 kHz; each slider trims +/-10 dB. RX / TX selector switches which path is being shaped.",
      "source_files": [
        "src/gui/EqApplet.cpp",
        "src/gui/EqApplet.h",
        "src/gui/GuardedSlider.h"
      ],
      "related_core_files": [
        "src/models/EqualizerModel.cpp",
        "src/models/EqualizerModel.h"
      ],
      "how_to_open": "Right sidebar applet tray button 'EQ' toggles the Equalizer tile. The tile sits in the top row of the applet panel.",
      "build_gate": null,
      "requires_radio_connection": true,
      "controls": [
        {
          "label": "ON",
          "kind": "toggle_button",
          "default": "unchecked",
          "valid_range": null,
          "setting_key": null,
          "behavior": "Enables or disables the equalizer for the currently-selected path (RX or TX).",
          "notes": "Green highlight when enabled. Acts on EqualizerModel::setTxEnabled / setRxEnabled depending on view."
        },
        {
          "label": "Reset arc (revert icon)",
          "kind": "push_button",
          "default": null,
          "valid_range": null,
          "setting_key": null,
          "behavior": "Resets all 8 bands of the currently-selected path back to 0 dB.",
          "notes": "Tooltip: 'Reset all bands to 0 dB'. Drawn as a 3/4-circle arrow."
        },
        {
          "label": "RX",
          "kind": "toggle_button",
          "default": "unchecked",
          "valid_range": null,
          "setting_key": null,
          "behavior": "Selects the receive equalizer bands for display / editing.",
          "notes": "Part of an exclusive pair with TX. Blue highlight when active."
        },
        {
          "label": "TX",
          "kind": "toggle_button",
          "default": "checked",
          "valid_range": null,
          "setting_key": null,
          "behavior": "Selects the transmit equalizer bands for display / editing.",
          "notes": "Starts checked — applet opens on the TX view."
        },
        {
          "label": "63",
          "kind": "slider",
          "default": "0",
          "valid_range": "-10 to +10 dB",
          "setting_key": null,
          "behavior": "Trims the 63 Hz band for the selected path; value label below slider updates live.",
          "notes": "Vertical slider, 100 px tall, no tick marks."
        },
        {
          "label": "125",
          "kind": "slider",
          "default": "0",
          "valid_range": "-10 to +10 dB",
          "setting_key": null,
          "behavior": "Trims the 125 Hz band for the selected path.",
          "notes": null
        },
        {
          "label": "250",
          "kind": "slider",
          "default": "0",
          "valid_range": "-10 to +10 dB",
          "setting_key": null,
          "behavior": "Trims the 250 Hz band for the selected path.",
          "notes": null
        },
        {
          "label": "500",
          "kind": "slider",
          "default": "0",
          "valid_range": "-10 to +10 dB",
          "setting_key": null,
          "behavior": "Trims the 500 Hz band for the selected path.",
          "notes": null
        },
        {
          "label": "1k",
          "kind": "slider",
          "default": "0",
          "valid_range": "-10 to +10 dB",
          "setting_key": null,
          "behavior": "Trims the 1 kHz band for the selected path.",
          "notes": null
        },
        {
          "label": "2k",
          "kind": "slider",
          "default": "0",
          "valid_range": "-10 to +10 dB",
          "setting_key": null,
          "behavior": "Trims the 2 kHz band for the selected path.",
          "notes": null
        },
        {
          "label": "4k",
          "kind": "slider",
          "default": "0",
          "valid_range": "-10 to +10 dB",
          "setting_key": null,
          "behavior": "Trims the 4 kHz band for the selected path.",
          "notes": null
        },
        {
          "label": "8k",
          "kind": "slider",
          "default": "0",
          "valid_range": "-10 to +10 dB",
          "setting_key": null,
          "behavior": "Trims the 8 kHz band for the selected path.",
          "notes": null
        },
        {
          "label": "+10 / 0 / -10 dB scale",
          "kind": "indicator",
          "default": null,
          "valid_range": null,
          "setting_key": null,
          "behavior": "Left and right reference labels showing the +/-10 dB range of the sliders.",
          "notes": null
        }
      ],
      "persisted_settings": [],
      "autostart_setting_key": null,
      "indicators": [
        {"label": "Per-band value label", "states": ["-10 through +10"], "meaning": "Live dB value of each slider shown below its handle."}
      ],
      "related_menu_items": [
        "Right-click the 'EQ' applet-tray button > toggle applet visibility"
      ],
      "related_user_tasks": [
        "Enable radio-side graphic EQ for TX",
        "Enable radio-side graphic EQ for RX",
        "Boost or cut specific octave bands (63 Hz to 8 kHz)",
        "Reset all bands to flat with one click",
        "Switch between shaping RX audio and TX audio",
        "Compare EQ on vs EQ off quickly with the ON button"
      ]
    }
  ]
}
